{
  "agent": "prd-themed-pattern-hunter",
  "featureSlug": "graphical-entries",
  "themes": [
    {
      "term": "lane",
      "occurrences": []
    },
    {
      "term": "deskwork",
      "occurrences": []
    },
    {
      "term": "stage",
      "occurrences": []
    },
    {
      "term": "entry",
      "occurrences": []
    },
    {
      "term": "entries",
      "occurrences": []
    },
    {
      "term": "pipeline",
      "occurrences": []
    },
    {
      "term": "studio",
      "occurrences": []
    },
    {
      "term": "surface",
      "occurrences": []
    },
    {
      "term": "iterate",
      "occurrences": []
    },
    {
      "term": "template",
      "occurrences": []
    },
    {
      "term": "graphical",
      "occurrences": []
    },
    {
      "term": "lanes",
      "occurrences": []
    }
  ]
}
