{
  "uuid": "35439a12-7b66-4563-a6d3-2ee33054dd45",
  "slug": "open-issue-tranche-cleanup/v016-verification-walk",
  "title": "v0.16.0 verification walk",
  "keywords": [],
  "source": "manual",
  "currentStage": "Drafting",
  "iterationByStage": {
    "Drafting": 1
  },
  "artifactPath": "docs/0.16.0/001-IN-PROGRESS/open-issue-tranche-cleanup/2026-05-05-v0.16.0-verification-walk.md",
  "createdAt": "2026-05-06T01:54:29.193Z",
  "updatedAt": "2026-05-06T02:02:39.275Z",
  "reviewState": "in-review"
}